dc_add_fields/__init__.py
dc_add_fields/add_fields.py
dc_add_fields-1.0.2.dist-info/METADATA
dc_add_fields-1.0.2.dist-info/WHEEL
dc_add_fields-1.0.2.dist-info/top_level.txt
dc_add_fields-1.0.2.dist-info/RECORD
