Metadata-Version: 2.1
Name: dc-add-fields
Version: 1.0.2
Summary: Datareader add_fields
Home-page: UNKNOWN
Author: Calyx
License: UNKNOWN
Platform: UNKNOWN
